LICENSE.txt
MANIFEST.in
README.rst
pyrfoutlet.py
rfoutlet_switch.py
setup.py
pyrfoutlet.egg-info/PKG-INFO
pyrfoutlet.egg-info/SOURCES.txt
pyrfoutlet.egg-info/dependency_links.txt
pyrfoutlet.egg-info/top_level.txt
source/RFOutlet.cpp
source/RFOutlet.h
source/daemon.h
source/rest.cpp