Metadata-Version: 1.1
Name: pyrfoutlet
Version: 0.0.2
Summary: A library for controlling Holiday Time rf outlets
Home-page: https://github.com/alanfischer/rfoutlet
Author: Alan Fischer
Author-email: alan@lightningtoads.com
License: MIT
Keywords: rf outlet
Platform: UNKNOWN
Classifier: Development Status :: 3 - Alpha
Classifier: Intended Audience :: Developers
Classifier: Topic :: Home Automation
Classifier: License :: OSI Approved :: MIT License
Classifier: Programming Language :: Python :: 2
Classifier: Programming Language :: Python :: 2.6
Classifier: Programming Language :: Python :: 2.7
Classifier: Programming Language :: Python :: 3
Classifier: Programming Language :: Python :: 3.3
Classifier: Programming Language :: Python :: 3.4
Classifier: Programming Language :: Python :: 3.5
